{"jobs": [[0, 1, 2, 3, 4, 5, 6, 7], [8, 9, 10, 11, 12, 13, 14, 15, 16, 17], [18, 19, 20, 21, 22, 23, 24], [25, 26, 27, 28, 29, 30, 31, 32, 33], [34, 35, 36, 37, 38, 39, 40, 41], [42, 43, 44, 45, 46, 47, 48, 49, 50, 51], [52, 53, 54, 55], [56, 57, 58, 59, 60, 61, 62, 63, 64], [65, 66, 67, 68, 69, 70, 71, 72, 73, 74], [75, 76, 77, 78, 79], [80, 81, 82, 83, 84, 85], [86, 87, 88, 89, 90, 91], [92, 93, 94, 95, 96, 97, 98, 99]], "operations": [[0, 0, 31, 0, 0, 0, 0, 0, 0, 0, 0], [80, 0, 0, 0, 0, 0, 0, 0, 0, 0, 0], [0, 0, 0, 0, 0, 0, 0, 83, 0, 0, 0], [0, 0, 0, 0, 0, 0, 0, 99, 0, 0, 0], [0, 0, 0, 0, 0, 0, 0, 50, 0, 0, 0], [0, 0, 0, 0, 0, 21, 0, 0, 0, 0, 0], [0, 0, 0, 0, 0, 0, 0, 0, 59, 0, 0], [0, 0, 0, 0, 0, 0, 0, 0, 0, 0, 5], [0, 0, 0, 0, 0, 0, 36, 0, 0, 0, 0], [0, 24, 0, 0, 0, 0, 0, 0, 0, 0, 0], [0, 0, 45, 0, 0, 0, 0, 0, 0, 0, 0], [0, 0, 0, 90, 0, 0, 0, 0, 0, 0, 0], [0, 0, 0, 0, 0, 0, 81, 0, 0, 0, 0], [0, 70, 0, 0, 0, 0, 0, 0, 0, 0, 0], [0, 0, 0, 0, 0, 0, 0, 0, 8, 0, 0], [0, 61, 0, 0, 0, 0, 0, 0, 0, 0, 0], [0, 0, 0, 0, 0, 0, 0, 53, 0, 0, 0], [0, 0, 0, 0, 0, 0, 70, 0, 0, 0, 0], [0, 0, 0, 0, 0, 0, 0, 0, 31, 0, 0], [0, 0, 0, 0, 0, 0, 33, 0, 0, 0, 0], [0, 0, 0, 0, 0, 0, 0, 0, 92, 0, 0], [0, 0, 0, 5, 0, 0, 0, 0, 0, 0, 0], [0, 0, 0, 0, 0, 73, 0, 0, 0, 0, 0], [0, 0, 0, 0, 0, 0, 0, 0, 0, 45, 0], [0, 0, 0, 7, 0, 0, 0, 0, 0, 0, 0], [0, 0, 0, 0, 0, 0, 0, 0, 53, 0, 0], [0, 0, 0, 0, 0, 0, 47, 0, 0, 0, 0], [0, 0, 0, 0, 0, 0, 0, 0, 0, 0, 57], [0, 0, 0, 0, 64, 0, 0, 0, 0, 0, 0], [0, 0, 0, 0, 0, 0, 0, 0, 0, 46, 0], [0, 0, 0, 0, 0, 0, 0, 51, 0, 0, 0], [0, 17, 0, 0, 0, 0, 0, 0, 0, 0, 0], [0, 0, 0, 0, 0, 0, 0, 0, 45, 0, 0], [0, 0, 0, 48, 0, 0, 0, 0, 0, 0, 0], [18, 0, 0, 0, 0, 0, 0, 0, 0, 0, 0], [73, 0, 0, 0, 0, 0, 0, 0, 0, 0, 0], [0, 87, 0, 0, 0, 0, 0, 0, 0, 0, 0], [0, 0, 0, 0, 0, 0, 72, 0, 0, 0, 0], [0, 0, 0, 0, 0, 0, 0, 0, 0, 54, 0], [0, 0, 0, 0, 0, 53, 0, 0, 0, 0, 0], [0, 0, 0, 0, 0, 0, 0, 0, 0, 0, 18], [0, 0, 21, 0, 0, 0, 0, 0, 0, 0, 0], [0, 0, 0, 0, 0, 0, 0, 15, 0, 0, 0], [0, 0, 0, 91, 0, 0, 0, 0, 0, 0, 0], [0, 0, 0, 0, 0, 0, 70, 0, 0, 0, 0], [0, 0, 0, 0, 0, 0, 0, 0, 0, 0, 80], [74, 0, 0, 0, 0, 0, 0, 0, 0, 0, 0], [0, 0, 0, 0, 0, 0, 0, 0, 0, 43, 0], [0, 0, 0, 26, 0, 0, 0, 0, 0, 0, 0], [0, 0, 12, 0, 0, 0, 0, 0, 0, 0, 0], [0, 0, 0, 0, 0, 46, 0, 0, 0, 0, 0], [0, 0, 0, 0, 30, 0, 0, 0, 0, 0, 0], [0, 0, 0, 0, 0, 21, 0, 0, 0, 0, 0], [0, 0, 0, 0, 0, 0, 0, 0, 0, 59, 0], [0, 0, 0, 0, 0, 0, 0, 0, 66, 0, 0], [0, 0, 0, 58, 0, 0, 0, 0, 0, 0, 0], [0, 0, 11, 0, 0, 0, 0, 0, 0, 0, 0], [0, 0, 0, 19, 0, 0, 0, 0, 0, 0, 0], [0, 87, 0, 0, 0, 0, 0, 0, 0, 0, 0], [0, 0, 0, 0, 0, 0, 0, 0, 0, 0, 92], [0, 0, 35, 0, 0, 0, 0, 0, 0, 0, 0], [0, 0, 0, 0, 0, 0, 0, 0, 0, 87, 0], [0, 0, 0, 0, 0, 0, 0, 0, 0, 86, 0], [0, 0, 0, 0, 0, 68, 0, 0, 0, 0, 0], [0, 0, 0, 0, 0, 0, 62, 0, 0, 0, 0], [0, 0, 0, 0, 0, 0, 0, 0, 66, 0, 0], [0, 0, 0, 69, 0, 0, 0, 0, 0, 0, 0], [0, 0, 0, 0, 0, 85, 0, 0, 0, 0, 0], [0, 0, 0, 0, 0, 0, 0, 0, 0, 64, 0], [0, 0, 0, 0, 0, 0, 0, 0, 0, 87, 0], [29, 0, 0, 0, 0, 0, 0, 0, 0, 0, 0], [0, 0, 0, 0, 33, 0, 0, 0, 0, 0, 0], [0, 0, 0, 0, 0, 0, 0, 42, 0, 0, 0], [40, 0, 0, 0, 0, 0, 0, 0, 0, 0, 0], [0, 0, 0, 0, 0, 0, 0, 21, 0, 0, 0], [0, 0, 0, 0, 0, 0, 0, 63, 0, 0, 0], [0, 0, 0, 0, 0, 0, 0, 0, 0, 27, 0], [0, 0, 0, 0, 0, 0, 79, 0, 0, 0, 0], [91, 0, 0, 0, 0, 0, 0, 0, 0, 0, 0], [0, 0, 35, 0, 0, 0, 0, 0, 0, 0, 0], [0, 0, 0, 0, 0, 0, 0, 0, 0, 0, 37], [0, 27, 0, 0, 0, 0, 0, 0, 0, 0, 0], [0, 0, 0, 0, 0, 0, 0, 0, 0, 94, 0], [0, 0, 0, 0, 0, 0, 0, 0, 0, 41, 0], [0, 0, 0, 0, 0, 0, 0, 77, 0, 0, 0], [0, 52, 0, 0, 0, 0, 0, 0, 0, 0, 0], [0, 5, 0, 0, 0, 0, 0, 0, 0, 0, 0], [0, 0, 0, 0, 0, 41, 0, 0, 0, 0, 0], [0, 0, 0, 0, 0, 0, 79, 0, 0, 0, 0], [0, 0, 0, 27, 0, 0, 0, 0, 0, 0, 0], [0, 0, 0, 0, 30, 0, 0, 0, 0, 0, 0], [0, 0, 0, 0, 0, 99, 0, 0, 0, 0, 0], [0, 0, 0, 0, 0, 0, 0, 0, 74, 0, 0], [0, 0, 0, 0, 0, 0, 0, 0, 63, 0, 0], [0, 0, 0, 0, 0, 53, 0, 0, 0, 0, 0], [0, 0, 0, 0, 0, 0, 0, 69, 0, 0, 0], [0, 0, 0, 0, 0, 0, 0, 35, 0, 0, 0], [0, 0, 0, 0, 0, 0, 0, 0, 0, 75, 0], [0, 0, 0, 0, 0, 0, 92, 0, 0, 0, 0], [0, 0, 0, 0, 0, 0, 0, 0, 0, 77, 0]], "optimal": "OPTIMAL", "score": 1427.0, "result": [{"job_id": "0", "task_id": 0, "start": 540, "end": 571, "machine": "2"}, {"job_id": "0", "task_id": 1, "start": 571, "end": 651, "machine": "0"}, {"job_id": "0", "task_id": 2, "start": 651, "end": 734, "machine": "7"}, {"job_id": "0", "task_id": 3, "start": 734, "end": 833, "machine": "7"}, {"job_id": "0", "task_id": 4, "start": 833, "end": 883, "machine": "7"}, {"job_id": "0", "task_id": 5, "start": 883, "end": 904, "machine": "5"}, {"job_id": "0", "task_id": 6, "start": 904, "end": 963, "machine": "8"}, {"job_id": "0", "task_id": 7, "start": 963, "end": 968, "machine": "10"}, {"job_id": "1", "task_id": 0, "start": 513, "end": 549, "machine": "6"}, {"job_id": "1", "task_id": 1, "start": 664, "end": 688, "machine": "1"}, {"job_id": "1", "task_id": 2, "start": 688, "end": 733, "machine": "2"}, {"job_id": "1", "task_id": 3, "start": 735, "end": 825, "machine": "3"}, {"job_id": "1", "task_id": 4, "start": 883, "end": 964, "machine": "6"}, {"job_id": "1", "task_id": 5, "start": 964, "end": 1034, "machine": "1"}, {"job_id": "1", "task_id": 6, "start": 1034, "end": 1042, "machine": "8"}, {"job_id": "1", "task_id": 7, "start": 1042, "end": 1103, "machine": "1"}, {"job_id": "1", "task_id": 8, "start": 1103, "end": 1156, "machine": "7"}, {"job_id": "1", "task_id": 9, "start": 1270, "end": 1340, "machine": "6"}, {"job_id": "2", "task_id": 0, "start": 451, "end": 482, "machine": "8"}, {"job_id": "2", "task_id": 1, "start": 549, "end": 582, "machine": "6"}, {"job_id": "2", "task_id": 2, "start": 804, "end": 896, "machine": "8"}, {"job_id": "2", "task_id": 3, "start": 896, "end": 901, "machine": "3"}, {"job_id": "2", "task_id": 4, "start": 904, "end": 977, "machine": "5"}, {"job_id": "2", "task_id": 5, "start": 1305, "end": 1350, "machine": "9"}, {"job_id": "2", "task_id": 6, "start": 1350, "end": 1357, "machine": "3"}, {"job_id": "3", "task_id": 0, "start": 548, "end": 601, "machine": "8"}, {"job_id": "3", "task_id": 1, "start": 662, "end": 709, "machine": "6"}, {"job_id": "3", "task_id": 2, "start": 756, "end": 813, "machine": "10"}, {"job_id": "3", "task_id": 3, "start": 813, "end": 877, "machine": "4"}, {"job_id": "3", "task_id": 4, "start": 968, "end": 1014, "machine": "9"}, {"job_id": "3", "task_id": 5, "start": 1157, "end": 1208, "machine": "7"}, {"job_id": "3", "task_id": 6, "start": 1208, "end": 1225, "machine": "1"}, {"job_id": "3", "task_id": 7, "start": 1225, "end": 1270, "machine": "8"}, {"job_id": "3", "task_id": 8, "start": 1357, "end": 1405, "machine": "3"}, {"job_id": "4", "task_id": 0, "start": 538, "end": 556, "machine": "0"}, {"job_id": "4", "task_id": 1, "start": 651, "end": 724, "machine": "0"}, {"job_id": "4", "task_id": 2, "start": 724, "end": 811, "machine": "1"}, {"job_id": "4", "task_id": 3, "start": 811, "end": 883, "machine": "6"}, {"job_id": "4", "task_id": 4, "start": 887, "end": 941, "machine": "9"}, {"job_id": "4", "task_id": 5, "start": 977, "end": 1030, "machine": "5"}, {"job_id": "4", "task_id": 6, "start": 1030, "end": 1048, "machine": "10"}, {"job_id": "4", "task_id": 7, "start": 1048, "end": 1069, "machine": "2"}, {"job_id": "5", "task_id": 0, "start": 570, "end": 585, "machine": "7"}, {"job_id": "5", "task_id": 1, "start": 617, "end": 708, "machine": "3"}, {"job_id": "5", "task_id": 2, "start": 709, "end": 779, "machine": "6"}, {"job_id": "5", "task_id": 3, "start": 813, "end": 893, "machine": "10"}, {"job_id": "5", "task_id": 4, "start": 893, "end": 967, "machine": "0"}, {"job_id": "5", "task_id": 5, "start": 1262, "end": 1305, "machine": "9"}, {"job_id": "5", "task_id": 6, "start": 1305, "end": 1331, "machine": "3"}, {"job_id": "5", "task_id": 7, "start": 1331, "end": 1343, "machine": "2"}, {"job_id": "5", "task_id": 8, "start": 1343, "end": 1389, "machine": "5"}, {"job_id": "5", "task_id": 9, "start": 1389, "end": 1419, "machine": "4"}, {"job_id": "6", "task_id": 0, "start": 521, "end": 542, "machine": "5"}, {"job_id": "6", "task_id": 1, "start": 542, "end": 601, "machine": "9"}, {"job_id": "6", "task_id": 2, "start": 738, "end": 804, "machine": "8"}, {"job_id": "6", "task_id": 3, "start": 825, "end": 883, "machine": "3"}, {"job_id": "7", "task_id": 0, "start": 481, "end": 492, "machine": "2"}, {"job_id": "7", "task_id": 1, "start": 492, "end": 511, "machine": "3"}, {"job_id": "7", "task_id": 2, "start": 577, "end": 664, "machine": "1"}, {"job_id": "7", "task_id": 3, "start": 664, "end": 756, "machine": "10"}, {"job_id": "7", "task_id": 4, "start": 756, "end": 791, "machine": "2"}, {"job_id": "7", "task_id": 5, "start": 800, "end": 887, "machine": "9"}, {"job_id": "7", "task_id": 6, "start": 1089, "end": 1175, "machine": "9"}, {"job_id": "7", "task_id": 7, "start": 1218, "end": 1286, "machine": "5"}, {"job_id": "7", "task_id": 8, "start": 1340, "end": 1402, "machine": "6"}, {"job_id": "8", "task_id": 0, "start": 482, "end": 548, "machine": "8"}, {"job_id": "8", "task_id": 1, "start": 548, "end": 617, "machine": "3"}, {"job_id": "8", "task_id": 2, "start": 617, "end": 702, "machine": "5"}, {"job_id": "8", "task_id": 3, "start": 736, "end": 800, "machine": "9"}, {"job_id": "8", "task_id": 4, "start": 1175, "end": 1262, "machine": "9"}, {"job_id": "8", "task_id": 5, "start": 1262, "end": 1291, "machine": "0"}, {"job_id": "8", "task_id": 6, "start": 1291, "end": 1324, "machine": "4"}, {"job_id": "8", "task_id": 7, "start": 1324, "end": 1366, "machine": "7"}, {"job_id": "8", "task_id": 8, "start": 1366, "end": 1406, "machine": "0"}, {"job_id": "8", "task_id": 9, "start": 1406, "end": 1427, "machine": "7"}, {"job_id": "9", "task_id": 0, "start": 585, "end": 648, "machine": "7"}, {"job_id": "9", "task_id": 1, "start": 941, "end": 968, "machine": "9"}, {"job_id": "9", "task_id": 2, "start": 1060, "end": 1139, "machine": "6"}, {"job_id": "9", "task_id": 3, "start": 1139, "end": 1230, "machine": "0"}, {"job_id": "9", "task_id": 4, "start": 1230, "end": 1265, "machine": "2"}, {"job_id": "10", "task_id": 0, "start": 513, "end": 550, "machine": "10"}, {"job_id": "10", "task_id": 1, "start": 550, "end": 577, "machine": "1"}, {"job_id": "10", "task_id": 2, "start": 601, "end": 695, "machine": "9"}, {"job_id": "10", "task_id": 3, "start": 695, "end": 736, "machine": "9"}, {"job_id": "10", "task_id": 4, "start": 987, "end": 1064, "machine": "7"}, {"job_id": "10", "task_id": 5, "start": 1103, "end": 1155, "machine": "1"}, {"job_id": "11", "task_id": 0, "start": 521, "end": 526, "machine": "1"}, {"job_id": "11", "task_id": 1, "start": 542, "end": 583, "machine": "5"}, {"job_id": "11", "task_id": 2, "start": 583, "end": 662, "machine": "6"}, {"job_id": "11", "task_id": 3, "start": 708, "end": 735, "machine": "3"}, {"job_id": "11", "task_id": 4, "start": 735, "end": 765, "machine": "4"}, {"job_id": "11", "task_id": 5, "start": 1030, "end": 1129, "machine": "5"}, {"job_id": "12", "task_id": 0, "start": 601, "end": 675, "machine": "8"}, {"job_id": "12", "task_id": 1, "start": 675, "end": 738, "machine": "8"}, {"job_id": "12", "task_id": 2, "start": 738, "end": 791, "machine": "5"}, {"job_id": "12", "task_id": 3, "start": 883, "end": 952, "machine": "7"}, {"job_id": "12", "task_id": 4, "start": 952, "end": 987, "machine": "7"}, {"job_id": "12", "task_id": 5, "start": 1014, "end": 1089, "machine": "9"}, {"job_id": "12", "task_id": 6, "start": 1178, "end": 1270, "machine": "6"}, {"job_id": "12", "task_id": 7, "start": 1350, "end": 1427, "machine": "9"}], "solution_sec": [0.010433518000000001, 0.012115815, 0.012948998000000001, 0.015481958, 0.015658036, 0.018020843, 0.01904374, 0.019291107000000002, 0.021152393000000002, 0.022683756000000003, 0.024397417, 0.026825728], "solution_score": [1562.0, 1558.0, 1519.0, 1515.0, 1500.0, 1496.0, 1482.0, 1472.0, 1470.0, 1463.0, 1432.0, 1427.0], "config": {"n_cases": 1, "range_jobs": [12, 13], "range_machines": [10, 11], "range_op_per_job": [12, 13], "processing_range": [5, 99], "min_options": 1, "max_options": 1}, "machines_starts": [538, 391, 481, 299, 0, 521, 513, 570, 451, 443, 424], "jobs_starts": [540, 425, 298, 299, 451, 419, 443, 481, 402, 570, 513, 521, 538]}