{"jobs": [[0, 1, 2, 3, 4, 5], [6, 7, 8, 9, 10, 11], [12, 13, 14, 15, 16, 17, 18, 19], [20, 21, 22, 23, 24, 25, 26], [27, 28, 29, 30, 31, 32, 33, 34, 35], [36, 37, 38, 39, 40, 41], [42, 43, 44, 45, 46, 47, 48, 49], [50, 51, 52, 53, 54, 55, 56], [57, 58, 59, 60, 61, 62, 63], [64, 65, 66, 67, 68, 69, 70, 71], [72, 73, 74, 75, 76, 77, 78], [79, 80, 81, 82, 83, 84, 85], [86, 87, 88, 89, 90, 91, 92, 93], [94, 95, 96, 97, 98, 99, 100, 101]], "operations": [[0, 0, 0, 0, 0, 0, 0, 0, 44, 0, 0, 0, 0], [0, 75, 0, 0, 0, 0, 0, 0, 0, 0, 0, 0, 0], [0, 0, 0, 0, 0, 6, 0, 0, 0, 0, 0, 0, 0], [0, 0, 0, 0, 0, 0, 0, 0, 93, 0, 0, 0, 0], [0, 0, 0, 0, 0, 0, 0, 0, 0, 0, 0, 0, 36], [0, 0, 0, 0, 0, 0, 0, 0, 0, 61, 0, 0, 0], [0, 0, 90, 0, 0, 0, 0, 0, 0, 0, 0, 0, 0], [0, 0, 0, 0, 0, 20, 0, 0, 0, 0, 0, 0, 0], [0, 0, 0, 84, 0, 0, 0, 0, 0, 0, 0, 0, 0], [0, 0, 0, 79, 0, 0, 0, 0, 0, 0, 0, 0, 0], [0, 0, 0, 0, 0, 0, 0, 0, 0, 0, 89, 0, 0], [0, 0, 0, 0, 0, 0, 0, 0, 0, 0, 0, 65, 0], [0, 0, 0, 57, 0, 0, 0, 0, 0, 0, 0, 0, 0], [0, 0, 0, 0, 0, 0, 0, 41, 0, 0, 0, 0, 0], [0, 0, 0, 0, 0, 0, 0, 0, 0, 0, 55, 0, 0], [0, 0, 0, 0, 0, 53, 0, 0, 0, 0, 0, 0, 0], [0, 0, 0, 0, 0, 0, 30, 0, 0, 0, 0, 0, 0], [0, 0, 0, 0, 0, 0, 84, 0, 0, 0, 0, 0, 0], [36, 0, 0, 0, 0, 0, 0, 0, 0, 0, 0, 0, 0], [0, 26, 0, 0, 0, 0, 0, 0, 0, 0, 0, 0, 0], [0, 0, 0, 0, 0, 0, 0, 0, 0, 0, 0, 27, 0], [0, 0, 0, 0, 0, 0, 0, 26, 0, 0, 0, 0, 0], [0, 0, 0, 0, 64, 0, 0, 0, 0, 0, 0, 0, 0], [0, 0, 0, 0, 0, 0, 0, 0, 0, 0, 0, 81, 0], [0, 0, 0, 0, 0, 0, 0, 0, 56, 0, 0, 0, 0], [0, 0, 48, 0, 0, 0, 0, 0, 0, 0, 0, 0, 0], [0, 0, 0, 0, 0, 39, 0, 0, 0, 0, 0, 0, 0], [0, 0, 0, 0, 0, 0, 0, 0, 7, 0, 0, 0, 0], [0, 35, 0, 0, 0, 0, 0, 0, 0, 0, 0, 0, 0], [0, 0, 0, 0, 0, 0, 0, 0, 0, 0, 0, 0, 52], [0, 0, 0, 0, 0, 0, 0, 0, 0, 0, 55, 0, 0], [0, 0, 0, 0, 0, 28, 0, 0, 0, 0, 0, 0, 0], [0, 0, 0, 0, 0, 0, 0, 0, 0, 0, 81, 0, 0], [0, 0, 0, 0, 0, 0, 0, 0, 24, 0, 0, 0, 0], [0, 0, 0, 58, 0, 0, 0, 0, 0, 0, 0, 0, 0], [0, 0, 0, 0, 0, 0, 0, 0, 0, 0, 77, 0, 0], [0, 0, 0, 0, 0, 0, 0, 0, 75, 0, 0, 0, 0], [0, 0, 0, 0, 0, 0, 0, 0, 0, 0, 12, 0, 0], [0, 86, 0, 0, 0, 0, 0, 0, 0, 0, 0, 0, 0], [0, 40, 0, 0, 0, 0, 0, 0, 0, 0, 0, 0, 0], [0, 0, 0, 0, 0, 0, 0, 70, 0, 0, 0, 0, 0], [0, 0, 0, 0, 0, 0, 0, 0, 0, 0, 0, 0, 66], [0, 0, 0, 0, 0, 69, 0, 0, 0, 0, 0, 0, 0], [93, 0, 0, 0, 0, 0, 0, 0, 0, 0, 0, 0, 0], [0, 0, 0, 0, 0, 0, 0, 0, 0, 0, 0, 91, 0], [7, 0, 0, 0, 0, 0, 0, 0, 0, 0, 0, 0, 0], [74, 0, 0, 0, 0, 0, 0, 0, 0, 0, 0, 0, 0], [0, 0, 0, 0, 0, 0, 0, 0, 0, 0, 0, 65, 0], [0, 0, 0, 0, 0, 0, 0, 0, 0, 0, 0, 31, 0], [0, 0, 0, 0, 0, 68, 0, 0, 0, 0, 0, 0, 0], [0, 75, 0, 0, 0, 0, 0, 0, 0, 0, 0, 0, 0], [0, 0, 0, 0, 0, 69, 0, 0, 0, 0, 0, 0, 0], [0, 0, 0, 0, 0, 0, 0, 14, 0, 0, 0, 0, 0], [0, 0, 0, 0, 0, 0, 0, 34, 0, 0, 0, 0, 0], [0, 0, 0, 0, 0, 50, 0, 0, 0, 0, 0, 0, 0], [0, 0, 54, 0, 0, 0, 0, 0, 0, 0, 0, 0, 0], [0, 0, 0, 0, 0, 88, 0, 0, 0, 0, 0, 0, 0], [0, 0, 0, 0, 0, 0, 0, 81, 0, 0, 0, 0, 0], [0, 0, 0, 0, 0, 61, 0, 0, 0, 0, 0, 0, 0], [0, 0, 0, 0, 0, 0, 0, 0, 0, 0, 32, 0, 0], [60, 0, 0, 0, 0, 0, 0, 0, 0, 0, 0, 0, 0], [0, 0, 0, 0, 0, 0, 0, 0, 0, 61, 0, 0, 0], [0, 0, 0, 0, 0, 0, 0, 0, 0, 91, 0, 0, 0], [0, 0, 0, 0, 0, 0, 0, 0, 0, 0, 23, 0, 0], [0, 0, 0, 0, 0, 0, 0, 0, 72, 0, 0, 0, 0], [0, 0, 0, 0, 0, 0, 0, 0, 0, 0, 25, 0, 0], [0, 0, 0, 0, 0, 0, 0, 0, 0, 5, 0, 0, 0], [0, 0, 0, 0, 0, 0, 0, 0, 0, 0, 0, 41, 0], [0, 0, 0, 0, 0, 0, 0, 89, 0, 0, 0, 0, 0], [53, 0, 0, 0, 0, 0, 0, 0, 0, 0, 0, 0, 0], [0, 0, 0, 0, 0, 36, 0, 0, 0, 0, 0, 0, 0], [0, 0, 51, 0, 0, 0, 0, 0, 0, 0, 0, 0, 0], [0, 0, 0, 0, 0, 48, 0, 0, 0, 0, 0, 0, 0], [0, 0, 0, 0, 0, 81, 0, 0, 0, 0, 0, 0, 0], [0, 0, 0, 0, 0, 0, 0, 0, 0, 0, 0, 28, 0], [85, 0, 0, 0, 0, 0, 0, 0, 0, 0, 0, 0, 0], [0, 0, 0, 0, 0, 0, 0, 0, 68, 0, 0, 0, 0], [0, 0, 0, 0, 0, 0, 68, 0, 0, 0, 0, 0, 0], [0, 0, 0, 0, 99, 0, 0, 0, 0, 0, 0, 0, 0], [0, 0, 0, 0, 0, 0, 0, 0, 0, 0, 6, 0, 0], [0, 0, 0, 0, 35, 0, 0, 0, 0, 0, 0, 0, 0], [0, 0, 0, 0, 0, 0, 0, 0, 0, 0, 56, 0, 0], [0, 0, 0, 0, 0, 0, 0, 0, 0, 32, 0, 0, 0], [0, 0, 0, 83, 0, 0, 0, 0, 0, 0, 0, 0, 0], [0, 0, 0, 0, 0, 15, 0, 0, 0, 0, 0, 0, 0], [0, 0, 0, 0, 0, 0, 0, 0, 0, 78, 0, 0, 0], [0, 0, 0, 0, 0, 0, 0, 0, 0, 0, 0, 14, 0], [0, 0, 0, 0, 0, 0, 0, 13, 0, 0, 0, 0, 0], [0, 0, 0, 0, 0, 0, 0, 0, 63, 0, 0, 0, 0], [0, 0, 0, 0, 0, 0, 0, 0, 0, 0, 0, 26, 0], [0, 86, 0, 0, 0, 0, 0, 0, 0, 0, 0, 0, 0], [0, 0, 0, 0, 0, 0, 0, 0, 40, 0, 0, 0, 0], [0, 0, 0, 0, 0, 0, 0, 0, 44, 0, 0, 0, 0], [0, 0, 0, 0, 0, 0, 0, 0, 56, 0, 0, 0, 0], [0, 0, 0, 0, 0, 0, 0, 0, 0, 7, 0, 0, 0], [0, 14, 0, 0, 0, 0, 0, 0, 0, 0, 0, 0, 0], [0, 0, 0, 0, 0, 0, 0, 0, 17, 0, 0, 0, 0], [80, 0, 0, 0, 0, 0, 0, 0, 0, 0, 0, 0, 0], [0, 0, 0, 0, 0, 0, 0, 0, 0, 0, 0, 27, 0], [0, 0, 0, 8, 0, 0, 0, 0, 0, 0, 0, 0, 0], [0, 6, 0, 0, 0, 0, 0, 0, 0, 0, 0, 0, 0], [0, 0, 0, 0, 0, 0, 0, 0, 0, 0, 82, 0, 0]], "optimal": "OPTIMAL", "score": 862.0, "result": [{"job_id": "0", "task_id": 0, "start": 198, "end": 242, "machine": "8"}, {"job_id": "0", "task_id": 1, "start": 242, "end": 317, "machine": "1"}, {"job_id": "0", "task_id": 2, "start": 649, "end": 655, "machine": "5"}, {"job_id": "0", "task_id": 3, "start": 659, "end": 752, "machine": "8"}, {"job_id": "0", "task_id": 4, "start": 752, "end": 788, "machine": "12"}, {"job_id": "0", "task_id": 5, "start": 788, "end": 849, "machine": "9"}, {"job_id": "1", "task_id": 0, "start": 36, "end": 126, "machine": "2"}, {"job_id": "1", "task_id": 1, "start": 131, "end": 151, "machine": "5"}, {"job_id": "1", "task_id": 2, "start": 168, "end": 252, "machine": "3"}, {"job_id": "1", "task_id": 3, "start": 252, "end": 331, "machine": "3"}, {"job_id": "1", "task_id": 4, "start": 579, "end": 668, "machine": "10"}, {"job_id": "1", "task_id": 5, "start": 746, "end": 811, "machine": "11"}, {"job_id": "2", "task_id": 0, "start": 111, "end": 168, "machine": "3"}, {"job_id": "2", "task_id": 1, "start": 237, "end": 278, "machine": "7"}, {"job_id": "2", "task_id": 2, "start": 317, "end": 372, "machine": "10"}, {"job_id": "2", "task_id": 3, "start": 546, "end": 599, "machine": "5"}, {"job_id": "2", "task_id": 4, "start": 599, "end": 629, "machine": "6"}, {"job_id": "2", "task_id": 5, "start": 705, "end": 789, "machine": "6"}, {"job_id": "2", "task_id": 6, "start": 789, "end": 825, "machine": "0"}, {"job_id": "2", "task_id": 7, "start": 825, "end": 851, "machine": "1"}, {"job_id": "3", "task_id": 0, "start": 90, "end": 117, "machine": "11"}, {"job_id": "3", "task_id": 1, "start": 117, "end": 143, "machine": "7"}, {"job_id": "3", "task_id": 2, "start": 184, "end": 248, "machine": "4"}, {"job_id": "3", "task_id": 3, "start": 252, "end": 333, "machine": "11"}, {"job_id": "3", "task_id": 4, "start": 380, "end": 436, "machine": "8"}, {"job_id": "3", "task_id": 5, "start": 436, "end": 484, "machine": "2"}, {"job_id": "3", "task_id": 6, "start": 507, "end": 546, "machine": "5"}, {"job_id": "4", "task_id": 0, "start": 102, "end": 109, "machine": "8"}, {"job_id": "4", "task_id": 1, "start": 109, "end": 144, "machine": "1"}, {"job_id": "4", "task_id": 2, "start": 144, "end": 196, "machine": "12"}, {"job_id": "4", "task_id": 3, "start": 206, "end": 261, "machine": "10"}, {"job_id": "4", "task_id": 4, "start": 329, "end": 357, "machine": "5"}, {"job_id": "4", "task_id": 5, "start": 416, "end": 497, "machine": "10"}, {"job_id": "4", "task_id": 6, "start": 529, "end": 553, "machine": "8"}, {"job_id": "4", "task_id": 7, "start": 553, "end": 611, "machine": "3"}, {"job_id": "4", "task_id": 8, "start": 668, "end": 745, "machine": "10"}, {"job_id": "5", "task_id": 0, "start": 305, "end": 380, "machine": "8"}, {"job_id": "5", "task_id": 1, "start": 404, "end": 416, "machine": "10"}, {"job_id": "5", "task_id": 2, "start": 451, "end": 537, "machine": "1"}, {"job_id": "5", "task_id": 3, "start": 537, "end": 577, "machine": "1"}, {"job_id": "5", "task_id": 4, "start": 578, "end": 648, "machine": "7"}, {"job_id": "5", "task_id": 5, "start": 648, "end": 714, "machine": "12"}, {"job_id": "6", "task_id": 0, "start": 151, "end": 220, "machine": "5"}, {"job_id": "6", "task_id": 1, "start": 278, "end": 371, "machine": "0"}, {"job_id": "6", "task_id": 2, "start": 466, "end": 557, "machine": "11"}, {"job_id": "6", "task_id": 3, "start": 569, "end": 576, "machine": "0"}, {"job_id": "6", "task_id": 4, "start": 576, "end": 650, "machine": "0"}, {"job_id": "6", "task_id": 5, "start": 650, "end": 715, "machine": "11"}, {"job_id": "6", "task_id": 6, "start": 715, "end": 746, "machine": "11"}, {"job_id": "6", "task_id": 7, "start": 794, "end": 862, "machine": "5"}, {"job_id": "7", "task_id": 0, "start": 158, "end": 233, "machine": "1"}, {"job_id": "7", "task_id": 1, "start": 438, "end": 507, "machine": "5"}, {"job_id": "7", "task_id": 2, "start": 507, "end": 521, "machine": "7"}, {"job_id": "7", "task_id": 3, "start": 521, "end": 555, "machine": "7"}, {"job_id": "7", "task_id": 4, "start": 599, "end": 649, "machine": "5"}, {"job_id": "7", "task_id": 5, "start": 649, "end": 703, "machine": "2"}, {"job_id": "7", "task_id": 6, "start": 706, "end": 794, "machine": "5"}, {"job_id": "8", "task_id": 0, "start": 143, "end": 224, "machine": "7"}, {"job_id": "8", "task_id": 1, "start": 268, "end": 329, "machine": "5"}, {"job_id": "8", "task_id": 2, "start": 372, "end": 404, "machine": "10"}, {"job_id": "8", "task_id": 3, "start": 424, "end": 484, "machine": "0"}, {"job_id": "8", "task_id": 4, "start": 484, "end": 545, "machine": "9"}, {"job_id": "8", "task_id": 5, "start": 545, "end": 636, "machine": "9"}, {"job_id": "8", "task_id": 6, "start": 745, "end": 768, "machine": "10"}, {"job_id": "9", "task_id": 0, "start": 109, "end": 181, "machine": "8"}, {"job_id": "9", "task_id": 1, "start": 181, "end": 206, "machine": "10"}, {"job_id": "9", "task_id": 2, "start": 206, "end": 211, "machine": "9"}, {"job_id": "9", "task_id": 3, "start": 211, "end": 252, "machine": "11"}, {"job_id": "9", "task_id": 4, "start": 278, "end": 367, "machine": "7"}, {"job_id": "9", "task_id": 5, "start": 371, "end": 424, "machine": "0"}, {"job_id": "9", "task_id": 6, "start": 670, "end": 706, "machine": "5"}, {"job_id": "9", "task_id": 7, "start": 706, "end": 757, "machine": "2"}, {"job_id": "10", "task_id": 0, "start": 220, "end": 268, "machine": "5"}, {"job_id": "10", "task_id": 1, "start": 357, "end": 438, "machine": "5"}, {"job_id": "10", "task_id": 2, "start": 438, "end": 466, "machine": "11"}, {"job_id": "10", "task_id": 3, "start": 484, "end": 569, "machine": "0"}, {"job_id": "10", "task_id": 4, "start": 569, "end": 637, "machine": "8"}, {"job_id": "10", "task_id": 5, "start": 637, "end": 705, "machine": "6"}, {"job_id": "10", "task_id": 6, "start": 705, "end": 804, "machine": "4"}, {"job_id": "11", "task_id": 0, "start": 143, "end": 149, "machine": "10"}, {"job_id": "11", "task_id": 1, "start": 149, "end": 184, "machine": "4"}, {"job_id": "11", "task_id": 2, "start": 261, "end": 317, "machine": "10"}, {"job_id": "11", "task_id": 3, "start": 317, "end": 349, "machine": "9"}, {"job_id": "11", "task_id": 4, "start": 349, "end": 432, "machine": "3"}, {"job_id": "11", "task_id": 5, "start": 655, "end": 670, "machine": "5"}, {"job_id": "11", "task_id": 6, "start": 670, "end": 748, "machine": "9"}, {"job_id": "12", "task_id": 0, "start": 36, "end": 50, "machine": "11"}, {"job_id": "12", "task_id": 1, "start": 224, "end": 237, "machine": "7"}, {"job_id": "12", "task_id": 2, "start": 242, "end": 305, "machine": "8"}, {"job_id": "12", "task_id": 3, "start": 333, "end": 359, "machine": "11"}, {"job_id": "12", "task_id": 4, "start": 359, "end": 445, "machine": "1"}, {"job_id": "12", "task_id": 5, "start": 445, "end": 485, "machine": "8"}, {"job_id": "12", "task_id": 6, "start": 485, "end": 529, "machine": "8"}, {"job_id": "12", "task_id": 7, "start": 752, "end": 808, "machine": "8"}, {"job_id": "13", "task_id": 0, "start": 114, "end": 121, "machine": "9"}, {"job_id": "13", "task_id": 1, "start": 144, "end": 158, "machine": "1"}, {"job_id": "13", "task_id": 2, "start": 181, "end": 198, "machine": "8"}, {"job_id": "13", "task_id": 3, "start": 198, "end": 278, "machine": "0"}, {"job_id": "13", "task_id": 4, "start": 359, "end": 386, "machine": "11"}, {"job_id": "13", "task_id": 5, "start": 432, "end": 440, "machine": "3"}, {"job_id": "13", "task_id": 6, "start": 445, "end": 451, "machine": "1"}, {"job_id": "13", "task_id": 7, "start": 497, "end": 579, "machine": "10"}], "solution_sec": [0.011277951000000001, 0.013167126000000001, 0.013824041, 0.015247080000000001, 0.016647249, 0.018880601, 0.019504601, 0.022126406, 0.023499195, 0.026086511000000003, 0.026226493, 0.02798561, 0.028656658, 0.030379714000000002, 0.032387745], "solution_score": [1095.0, 1092.0, 952.0, 951.0, 928.0, 921.0, 899.0, 895.0, 885.0, 880.0, 879.0, 877.0, 874.0, 872.0, 862.0], "config": {"n_cases": 1, "range_jobs": [13, 14], "range_machines": [13, 14], "range_op_per_job": [8, 9], "processing_range": [5, 99], "min_options": 1, "max_options": 1}, "machines_starts": [114, 62, 21, 111, 90, 131, 0, 117, 102, 0, 143, 36, 0], "jobs_starts": [131, 36, 0, 90, 0, 143, 87, 117, 111, 102, 59, 70, 0, 114]}